telegrambotapiwrapper/__init__.py
telegrambotapiwrapper/annotation.py
telegrambotapiwrapper/base.py
telegrambotapiwrapper/errors.py
telegrambotapiwrapper/frames.py
telegrambotapiwrapper/printpretty.py
telegrambotapiwrapper/proxies.py
telegrambotapiwrapper/request.py
telegrambotapiwrapper/response.py
telegrambotapiwrapper/typelib.py
telegrambotapiwrapper/webhooks.py
tests/__init__.py
tests/run_all_tests.py
tests/test_annotation.py
tests/test_frames.py
tests/test_request.py
tests/test_response.py
tests/test_utils.py
tests/test_webhooks.py
telegrambotapiwrapper-0.5.0.dist-info/AUTHORS.rst
telegrambotapiwrapper-0.5.0.dist-info/LICENSE
telegrambotapiwrapper-0.5.0.dist-info/METADATA
telegrambotapiwrapper-0.5.0.dist-info/WHEEL
telegrambotapiwrapper-0.5.0.dist-info/top_level.txt
telegrambotapiwrapper-0.5.0.dist-info/RECORD
