Metadata-Version: 2.1
Name: telegrambotapiwrapper
Version: 0.5.0
Summary: Python Telegram Bot Api Wrapper.
Home-page: https://github.com/pynista/telegrambotapiwrapper
Author: Dzmitry Maliuzhenets
Author-email: dzmitrymaliuzhenets@gmail.com
License: UNKNOWN
Keywords: telegram api bot wrapper
Platform: UNKNOWN
Classifier: Development Status :: 5 - Production/Stable
Classifier: Intended Audience :: Developers
Classifier: Natural Language :: English
Classifier: Natural Language :: Russian
Classifier: License :: OSI Approved :: MIT License
Classifier: Programming Language :: Python :: 3.7
Classifier: Programming Language :: Python :: 3.8
Classifier: Programming Language :: Python :: 3.9
Classifier: Programming Language :: Python :: Implementation :: CPython
Classifier: Operating System :: OS Independent
Requires-Python: ~=3.7
Requires-Dist: prettyprinter
Requires-Dist: jsonpickle
Requires-Dist: requests
